{
  "tasks": [
    {
      "name": "Welcome to Todo App. You can add new tasks.",
      "id": "1",
      "completed": false
    },
    {
      "name": "New task just to test everything works as expected.",
      "createdAt": 1482554677202,
      "id": "Bkp4pdj4g",
      "completed": true
    },
    {
      "name": "Another task to test out the new addTask action handler.",
      "completed": true,
      "createdAt": 1482554912369,
      "id": "H1u7ROoEl"
    },
    {
      "name": "Task to test out a simplified task addition.",
      "completed": false,
      "createdAt": 1482555446331,
      "id": "SJ0EeFo4e"
    }
  ]
}